odoo/addons/rma_delivery/README.rst
odoo/addons/rma_delivery/__init__.py
odoo/addons/rma_delivery/__manifest__.py
odoo/addons/rma_delivery/i18n/es.po
odoo/addons/rma_delivery/i18n/it.po
odoo/addons/rma_delivery/i18n/rma_delivery.pot
odoo/addons/rma_delivery/models/__init__.py
odoo/addons/rma_delivery/models/res_company.py
odoo/addons/rma_delivery/models/res_config_settings.py
odoo/addons/rma_delivery/models/rma.py
odoo/addons/rma_delivery/models/stock_move.py
odoo/addons/rma_delivery/readme/CONFIGURE.md
odoo/addons/rma_delivery/readme/CONTRIBUTORS.md
odoo/addons/rma_delivery/readme/DESCRIPTION.md
odoo/addons/rma_delivery/readme/USAGE.md
odoo/addons/rma_delivery/static/description/icon.png
odoo/addons/rma_delivery/static/description/index.html
odoo/addons/rma_delivery/tests/__init__.py
odoo/addons/rma_delivery/tests/test_rma_delivery.py
odoo/addons/rma_delivery/views/res_config_settings_views.xml
odoo/addons/rma_delivery/views/rma_views.xml
odoo_addon_rma_delivery-18.0.1.0.0.5.dist-info/METADATA
odoo_addon_rma_delivery-18.0.1.0.0.5.dist-info/WHEEL
odoo_addon_rma_delivery-18.0.1.0.0.5.dist-info/top_level.txt
odoo_addon_rma_delivery-18.0.1.0.0.5.dist-info/RECORD
